{
    "text": " If you're talking about the share of the entity with the share, like I shared with the previous Is ByteDance part of the corporate group? ByteDance as a holding company is part of the corporate group, yes.",
    "segments": [
        {
            "id": 0,
            "seek": 0,
            "start": 0.0,
            "end": 6.36,
            "text": " If you're talking about the share of the entity with the share, like I shared with the previous",
            "tokens": [
                50364,
                759,
                291,
                434,
                1417,
                466,
                264,
                2073,
                295,
                264,
                13977,
                365,
                264,
                2073,
                11,
                411,
                286,
                5507,
                365,
                264,
                3894,
                50688
            ],
            "temperature": 0.0,
            "avg_logprob": -0.38334763266823507,
            "compression_ratio": 1.6015625,
            "no_speech_prob": 0.03120272047817707,
            "words": [
                {
                    "word": " If",
                    "start": 0.0,
                    "end": 0.22,
                    "probability": 0.36206552386283875
                },
                {
                    "word": " you're",
                    "start": 0.22,
                    "end": 0.34,
                    "probability": 0.8183712363243103
                },
                {
                    "word": " talking",
                    "start": 0.34,
                    "end": 0.56,
                    "probability": 0.773140549659729
                },
                {
                    "word": " about",
                    "start": 0.56,
                    "end": 0.78,
                    "probability": 0.8267676830291748
                },
                {
                    "word": " the",
                    "start": 0.78,
                    "end": 1.22,
                    "probability": 0.739915132522583
                },
                {
                    "word": " share",
                    "start": 1.22,
                    "end": 1.62,
                    "probability": 0.7144299745559692
                },
                {
                    "word": " of",
                    "start": 1.62,
                    "end": 1.78,
                    "probability": 0.735129177570343
                },
                {
                    "word": " the",
                    "start": 1.78,
                    "end": 2.3,
                    "probability": 0.8059279918670654
                },
                {
                    "word": " entity",
                    "start": 2.3,
                    "end": 2.84,
                    "probability": 0.8429611325263977
                },
                {
                    "word": " with",
                    "start": 2.84,
                    "end": 3.24,
                    "probability": 0.6189173460006714
                },
                {
                    "word": " the",
                    "start": 3.24,
                    "end": 3.96,
                    "probability": 0.7876623272895813
                },
                {
                    "word": " share,",
                    "start": 3.96,
                    "end": 4.22,
                    "probability": 0.7593795657157898
                },
                {
                    "word": " like",
                    "start": 4.8,
                    "end": 5.1,
                    "probability": 0.8072863817214966
                },
                {
                    "word": " I",
                    "start": 5.1,
                    "end": 5.22,
                    "probability": 0.9630327820777893
                },
                {
                    "word": " shared",
                    "start": 5.22,
                    "end": 5.44,
                    "probability": 0.7679662704467773
                },
                {
                    "word": " with",
                    "start": 5.44,
                    "end": 5.7,
                    "probability": 0.790505051612854
                },
                {
                    "word": " the",
                    "start": 5.7,
                    "end": 6.08,
                    "probability": 0.8057202100753784
                },
                {
                    "word": " previous",
                    "start": 6.08,
                    "end": 6.36,
                    "probability": 0.8350263833999634
                }
            ]
        },
        {
            "id": 1,
            "seek": 0,
            "start": 6.36,
            "end": 8.98,
            "text": " Is ByteDance part of the corporate group?",
            "tokens": [
                50688,
                1119,
                3146,
                975,
                35,
                719,
                644,
                295,
                264,
                10896,
                1594,
                30,
                50848
            ],
            "temperature": 0.0,
            "avg_logprob": -0.38334763266823507,
            "compression_ratio": 1.6015625,
            "no_speech_prob": 0.03120272047817707,
            "words": [
                {
                    "word": " Is",
                    "start": 6.36,
                    "end": 6.9,
                    "probability": 0.05011911690235138
                },
                {
                    "word": " ByteDance",
                    "start": 6.9,
                    "end": 7.38,
                    "probability": 0.9267522990703583
                },
                {
                    "word": " part",
                    "start": 7.38,
                    "end": 7.66,
                    "probability": 0.8062902092933655
                },
                {
                    "word": " of",
                    "start": 7.66,
                    "end": 7.92,
                    "probability": 0.9004875421524048
                },
                {
                    "word": " the",
                    "start": 7.92,
                    "end": 8.1,
                    "probability": 0.8129639029502869
                },
                {
                    "word": " corporate",
                    "start": 8.1,
                    "end": 8.5,
                    "probability": 0.8678622245788574
                },
                {
                    "word": " group?",
                    "start": 8.5,
                    "end": 8.98,
                    "probability": 0.8556174635887146
                }
            ]
        },
        {
            "id": 2,
            "seek": 0,
            "start": 9.6,
            "end": 13.02,
            "text": " ByteDance as a holding company is part of the corporate group, yes.",
            "tokens": [
                50848,
                3146,
                975,
                35,
                719,
                382,
                257,
                5061,
                2237,
                307,
                644,
                295,
                264,
                10896,
                1594,
                11,
                2086,
                13,
                51040
            ],
            "temperature": 0.0,
            "avg_logprob": -0.38334763266823507,
            "compression_ratio": 1.6015625,
            "no_speech_prob": 0.03120272047817707,
            "words": [
                {
                    "word": " ByteDance",
                    "start": 9.6,
                    "end": 10.22,
                    "probability": 0.9294115453958511
                },
                {
                    "word": " as",
                    "start": 10.22,
                    "end": 10.42,
                    "probability": 0.6783581972122192
                },
                {
                    "word": " a",
                    "start": 10.42,
                    "end": 10.62,
                    "probability": 0.974809467792511
                },
                {
                    "word": " holding",
                    "start": 10.62,
                    "end": 10.84,
                    "probability": 0.7517634630203247
                },
                {
                    "word": " company",
                    "start": 10.84,
                    "end": 11.24,
                    "probability": 0.812533438205719
                },
                {
                    "word": " is",
                    "start": 11.24,
                    "end": 12.02,
                    "probability": 0.5373144745826721
                },
                {
                    "word": " part",
                    "start": 12.02,
                    "end": 12.28,
                    "probability": 0.8058947920799255
                },
                {
                    "word": " of",
                    "start": 12.28,
                    "end": 12.38,
                    "probability": 0.9069575071334839
                },
                {
                    "word": " the",
                    "start": 12.38,
                    "end": 12.48,
                    "probability": 0.8035872578620911
                },
                {
                    "word": " corporate",
                    "start": 12.48,
                    "end": 12.66,
                    "probability": 0.8781409859657288
                },
                {
                    "word": " group,",
                    "start": 12.66,
                    "end": 12.84,
                    "probability": 0.7763211727142334
                },
                {
                    "word": " yes.",
                    "start": 12.9,
                    "end": 13.02,
                    "probability": 0.896206259727478
                }
            ]
        }
    ],
    "language": "en"
}